[
  {
    "label": "mobile-0",
    "scrollY": 0,
    "scrollHeight": 17416,
    "bodyH1": "Build a Spark cluster you can fly through.",
    "viewport": {
      "w": 472,
      "h": 1023
    },
    "mostVisibleSection": {
      "id": "hero",
      "index": 1,
      "top": 488.125,
      "bottom": 1949.71875,
      "visHeight": 534.875,
      "ratio": 0.5228494623655914,
      "inViewport": true
    },
    "closestH2": {
      "text": "A cluster, asleep.",
      "y": 844.921875,
      "sceneId": "hero",
      "inViewport": true
    },
    "visibleH2Sceneid": "hero",
    "activeKickerLabel": "Jump to scene 1: A cluster, asleep.",
    "activeKickerText": "01 · The cluster",
    "aligned": false
  },
  {
    "label": "mobile-33",
    "scrollY": 5479,
    "scrollHeight": 17416,
    "bodyH1": "Build a Spark cluster you can fly through.",
    "viewport": {
      "w": 472,
      "h": 1023
    },
    "mostVisibleSection": {
      "id": "data-arrival",
      "index": 4,
      "top": -606.09375,
      "bottom": 855.5,
      "visHeight": 855.5,
      "ratio": 0.8362658846529815,
      "inViewport": true
    },
    "closestH2": {
      "text": "A terabyte arrives.",
      "y": 178.15625,
      "sceneId": "data-arrival",
      "inViewport": true
    },
    "visibleH2Sceneid": "data-arrival",
    "activeKickerLabel": "Jump to scene 4: A terabyte arrives.",
    "activeKickerText": "04 · The data",
    "aligned": false
  },
  {
    "label": "mobile-50",
    "scrollY": 8302,
    "scrollHeight": 17416,
    "bodyH1": "Build a Spark cluster you can fly through.",
    "viewport": {
      "w": 472,
      "h": 1023
    },
    "mostVisibleSection": {
      "id": "task-rain",
      "index": 6,
      "top": -505.90625,
      "bottom": 955.6875,
      "visHeight": 955.6875,
      "ratio": 0.9342008797653959,
      "inViewport": true
    },
    "closestH2": {
      "text": "Tasks, in parallel.",
      "y": 178.15625,
      "sceneId": "task-rain",
      "inViewport": true
    },
    "visibleH2Sceneid": "task-rain",
    "activeKickerLabel": "Jump to scene 6: Tasks, in parallel.",
    "activeKickerText": "06 · Parallelism",
    "aligned": false
  },
  {
    "label": "mobile-75",
    "scrollY": 12453,
    "scrollHeight": 17416,
    "bodyH1": "Build a Spark cluster you can fly through.",
    "viewport": {
      "w": 472,
      "h": 1023
    },
    "mostVisibleSection": {
      "id": "stages",
      "index": 9,
      "top": -272.125,
      "bottom": 1189.46875,
      "visHeight": 1023,
      "ratio": 1,
      "inViewport": true
    },
    "closestH2": {
      "text": "Stages, drawn on the air.",
      "y": 178.15625,
      "sceneId": "stages",
      "inViewport": true
    },
    "visibleH2Sceneid": "stages",
    "activeKickerLabel": "Jump to scene 9: Stages, drawn on the air.",
    "activeKickerText": "09 · Stages",
    "aligned": false
  }
]